{"vehicule":[{"localisation":{"lat":35.14312716931114,"lng":-90.00732061458714,"cap":94},"conduite":{"idLigne":90301,"vitesse":2,"destination":"EXETER RD @ POPLAR AVE","avanceRetard":"5 min late","arretSuiv":{"nomCommercial":"POPLAR @ANGELUS","estimationTemps":0}},"id":21021,"vehiculeLoad":"36%","type":"Bus","numeroEquipement":"4016"},{"localisation":{"lat":35.091462552967364,"lng":-90.05637202807108,"cap":185},"conduite":{"idLigne":90299,"vitesse":15,"destination":"JONETTA ST @ HOLMES RD","avanceRetard":"on time","arretSuiv":{"nomCommercial":"THIRD @FRANK","estimationTemps":0}},"id":20020,"vehiculeLoad":"6%","type":"Bus","numeroEquipement":"4017"},{"localisation":{"lat":35.16003413148778,"lng":-89.9626980319264,"cap":71},"conduite":{"idLigne":90302,"vitesse":15,"destination":"METHODIST HOSPI","avanceRetard":"on time","arretSuiv":{"nomCommercial":"JACKSON @TILLMAN","estimationTemps":0}},"id":19037,"vehiculeLoad":"14%","type":"Bus","numeroEquipement":"4028"},{"localisation":{"lat":35.119590249853466,"lng":-90.03882556031864,"cap":156},"conduite":{"idLigne":90290,"vitesse":2,"destination":"AIRWAYS TRANSIT","avanceRetard":"4 min late","arretSuiv":{"nomCommercial":"MISSISSIPPI BLV @WALKER","estimationTemps":0}},"id":10011,"vehiculeLoad":"12%","type":"Bus","numeroEquipement":"21707"},{"localisation":{"lat":35.19919202583062,"lng":-89.97901728232455,"cap":272},"conduite":{"idLigne":90294,"vitesse":12,"destination":"ALICE AVE @ BENTON ST","avanceRetard":"2 min late","arretSuiv":{"nomCommercial":"JAMES @W SKYLINE CIR","estimationTemps":0}},"id":10013,"vehiculeLoad":"6%","type":"Bus","numeroEquipement":"21705"},{"localisation":{"lat":35.17715200999743,"lng":-89.97537555320916,"cap":189},"conduite":{"idLigne":90296,"vitesse":0,"destination":"AIRWAYS TRANSIT","avanceRetard":"5 min early","arretSuiv":{"nomCommercial":"HOLLYWOOD @CHELSEA","estimationTemps":0}},"id":10015,"vehiculeLoad":"20%","type":"Bus","numeroEquipement":"21703"},{"localisation":{"lat":35.096453375863675,"lng":-89.82333317501335,"cap":278},"conduite":{"idLigne":90301,"vitesse":5,"destination":"WILLIAM HUDSON ","avanceRetard":"on time","arretSuiv":{"nomCommercial":"POPLAR @POPLAR ESTATES","estimationTemps":0}},"id":10016,"vehiculeLoad":"2%","type":"Bus","numeroEquipement":"21702"},{"localisation":{"lat":35.062274798390575,"lng":-89.99205909380933,"cap":81},"conduite":{"idLigne":90296,"vitesse":0,"destination":"FRAYSER PLAZA","avanceRetard":"5 min late","arretSuiv":{"nomCommercial":"AIRWAYS BLVD @BROOKS","estimationTemps":0}},"id":10017,"vehiculeLoad":"0%","type":"Bus","numeroEquipement":"21701"},{"localisation":{"lat":35.13594663521596,"lng":-90.00812335438475,"cap":96},"conduite":{"idLigne":90288,"vitesse":13,"destination":"WALNUT @ RACINE","avanceRetard":"5 min late","arretSuiv":{"nomCommercial":"UNION AVE @BELVEDERE BLVD","estimationTemps":0}},"id":10021,"vehiculeLoad":"16%","type":"Bus","numeroEquipement":"21712"},{"localisation":{"lat":35.13016550860242,"lng":-89.95368742530582,"cap":291},"conduite":{"idLigne":90301,"vitesse":13,"destination":"WILLIAM HUDSON ","avanceRetard":"on time","arretSuiv":{"nomCommercial":"POPLAR @MARNE","estimationTemps":0}},"id":10022,"vehiculeLoad":"0%","type":"Bus","numeroEquipement":"21711"},{"localisation":{"lat":35.20815028145337,"lng":-90.00357598192268,"cap":113},"conduite":{"idLigne":90296,"vitesse":5,"destination":"FRAYSER PLAZA","avanceRetard":"on time","arretSuiv":{"nomCommercial":"WHITNEY @EDEN","estimationTemps":0}},"id":10026,"vehiculeLoad":"12%","type":"Bus","numeroEquipement":"21708"},{"localisation":{"lat":35.115633830104976,"lng":-90.03762400010376,"cap":92},"conduite":{"idLigne":90286,"vitesse":13,"destination":"PRIMACY PKWY @ RIDGEWAY RD","avanceRetard":"5 min late","arretSuiv":{"nomCommercial":"MCLEMORE @MISSISSIPPI BL","estimationTemps":0}},"id":10031,"vehiculeLoad":"16%","type":"Bus","numeroEquipement":"21805"},{"localisation":{"lat":35.18635180119919,"lng":-89.89615919329138,"cap":4},"conduite":{"idLigne":90298,"vitesse":0,"destination":"YALE RD @ AUSTIN PEAY HW","avanceRetard":"on time","arretSuiv":{"nomCommercial":"COVINGTON PIKE @CHISWOOD","estimationTemps":0}},"id":10035,"vehiculeLoad":"22%","type":"Bus","numeroEquipement":"21801"},{"localisation":{"lat":35.0552073990538,"lng":-90.02502828850425,"cap":185},"conduite":{"idLigne":90300,"vitesse":7,"destination":"AIRWAYS TRANSIT","avanceRetard":"on time","arretSuiv":{"nomCommercial":"ELVIS PRESLEY @WINCHESTER","estimationTemps":0}},"id":10043,"vehiculeLoad":"30%","type":"Bus","numeroEquipement":"21808"},{"localisation":{"lat":35.1281336770559,"lng":-90.06184268338244,"cap":182},"conduite":{"idLigne":90282,"vitesse":4,"destination":"AIRWAYS TRANSIT","avanceRetard":"8 min late","arretSuiv":{"nomCommercial":"FLORIDA @VIRGINIA","estimationTemps":0}},"id":10046,"vehiculeLoad":"6%","type":"Bus","numeroEquipement":"428"},{"localisation":{"lat":35.10829792254692,"lng":-89.97690354000233,"cap":269},"conduite":{"idLigne":90286,"vitesse":6,"destination":"WILLIAM HUDSON ","avanceRetard":"on time","arretSuiv":{"nomCommercial":"PARK @HAMILTON","estimationTemps":0}},"id":10048,"vehiculeLoad":"12%","type":"Bus","numeroEquipement":"21501"},{"localisation":{"lat":35.17067382881178,"lng":-90.0090580592327,"cap":203},"conduite":{"idLigne":90300,"vitesse":16,"destination":"AIRWAYS TRANSIT","avanceRetard":"7 min late","arretSuiv":{"nomCommercial":"WATKINS @LEXINGTON CIR","estimationTemps":0}},"id":10053,"vehiculeLoad":"18%","type":"Bus","numeroEquipement":"21502"},{"localisation":{"lat":35.106134444258835,"lng":-89.91569748348367,"cap":359},"conduite":{"idLigne":90289,"vitesse":0,"destination":"WILLIAM HUDSON ","avanceRetard":"2 min early","arretSuiv":{"nomCommercial":"PARK @CHERRY","estimationTemps":0}},"id":10054,"vehiculeLoad":"4%","type":"Bus","numeroEquipement":"431"},{"localisation":{"lat":35.09199739111478,"lng":-90.00293795860594,"cap":272},"conduite":{"idLigne":90290,"vitesse":14,"destination":"WILLIAM HUDSON ","avanceRetard":"4 min late","arretSuiv":{"nomCommercial":"PERRY @DUNN","estimationTemps":1}},"id":8014,"vehiculeLoad":"6%","type":"Bus","numeroEquipement":"21713"},{"localisation":{"lat":35.062306894609065,"lng":-89.99224217494097,"cap":88},"conduite":{"idLigne":90300,"vitesse":0,"destination":"FRAYSER at WOODROW","avanceRetard":"5 min late","arretSuiv":{"nomCommercial":"AIRWAYS BLVD @WINCHESTER","estimationTemps":1}},"id":10065,"vehiculeLoad":"0%","type":"Bus","numeroEquipement":"4020"},{"localisation":{"lat":35.17344284442398,"lng":-89.95363808906485,"cap":273},"conduite":{"idLigne":90292,"vitesse":0,"destination":"WILLIAM HUDSON ","avanceRetard":"6 min late","arretSuiv":{"nomCommercial":"CHELSEA AVE @BROOKINS","estimationTemps":0}},"id":10073,"vehiculeLoad":"4%","type":"Bus","numeroEquipement":"442"},{"localisation":{"lat":35.17468291153775,"lng":-89.98215570888576,"cap":80},"conduite":{"idLigne":90292,"vitesse":13,"destination":"AMERICAN WAY TR","avanceRetard":"5 min late","arretSuiv":{"nomCommercial":"CHELSEA @PERES","estimationTemps":0}},"id":10074,"vehiculeLoad":"16%","type":"Bus","numeroEquipement":"443"},{"localisation":{"lat":35.14268362450696,"lng":-90.03095080639561,"cap":263},"conduite":{"idLigne":90297,"vitesse":13,"destination":"WILLIAM HUDSON ","avanceRetard":"9 min late","arretSuiv":{"nomCommercial":"JEFFERSON @DUNLAP","estimationTemps":0}},"id":10075,"vehiculeLoad":"14%","type":"Bus","numeroEquipement":"444"},{"localisation":{"lat":35.15263891306648,"lng":-89.99933805527057,"cap":95},"conduite":{"idLigne":90303,"vitesse":7,"destination":"SWTCC","avanceRetard":"9 min late","arretSuiv":{"nomCommercial":"N PARKWAY @MC LEAN","estimationTemps":0}},"id":10077,"vehiculeLoad":"38%","type":"Bus","numeroEquipement":"446"},{"localisation":{"lat":35.123413896501866,"lng":-89.9455095164105,"cap":182},"conduite":{"idLigne":90305,"vitesse":8,"destination":"WILLIAM HUDSON ","avanceRetard":"2 min late","arretSuiv":{"nomCommercial":"CENTRAL AVE @WINDOVER RD","estimationTemps":0}},"id":10083,"vehiculeLoad":"0%","type":"Bus","numeroEquipement":"449"},{"localisation":{"lat":35.14909577760279,"lng":-89.92298891937394,"cap":272},"conduite":{"idLigne":90303,"vitesse":0,"destination":"WILLIAM HUDSON ","avanceRetard":"on time","arretSuiv":{"nomCommercial":"SUMMER AVE @NGRAHAM ST","estimationTemps":0}},"id":10105,"vehiculeLoad":"8%","type":"Bus","numeroEquipement":"451"},{"localisation":{"lat":35.092906616347214,"lng":-90.06573463428785,"cap":251},"conduite":{"idLigne":90282,"vitesse":15,"destination":"WILLIAM HUDSON ","avanceRetard":"on time","arretSuiv":{"nomCommercial":"BELZ @KANSAS","estimationTemps":0}},"id":10107,"vehiculeLoad":"14%","type":"Bus","numeroEquipement":"453"},{"localisation":{"lat":35.138507566423556,"lng":-90.01232910683353,"cap":96},"conduite":{"idLigne":90289,"vitesse":6,"destination":"CENTRAL AVE @ U-M CROSSWALK","avanceRetard":"5 min late","arretSuiv":{"nomCommercial":"MADISON @WILLET","estimationTemps":0}},"id":10109,"vehiculeLoad":"22%","type":"Bus","numeroEquipement":"454"},{"localisation":{"lat":35.148674013442985,"lng":-90.01444253475326,"cap":7},"conduite":{"idLigne":90300,"vitesse":4,"destination":"FRAYSER at WOODROW","avanceRetard":"on time","arretSuiv":{"nomCommercial":"CLEVELAND @OVERTON PARK","estimationTemps":0}},"id":10111,"vehiculeLoad":"18%","type":"Bus","numeroEquipement":"456"},{"localisation":{"lat":35.07922110754001,"lng":-89.9028313481642,"cap":329},"conduite":{"idLigne":90297,"vitesse":6,"destination":"CENTENNIAL DR @ HACKS CROSS RD","avanceRetard":"on time","arretSuiv":{"nomCommercial":"EXCEL CENTER","estimationTemps":0}},"id":10118,"vehiculeLoad":"6%","type":"Bus","numeroEquipement":"4029"},{"localisation":{"lat":35.0423949857554,"lng":-90.02505954530062,"cap":0},"conduite":{"idLigne":90300,"vitesse":17,"destination":"FRAYSER at WOODROW","avanceRetard":"on time","arretSuiv":{"nomCommercial":"ELVIS PRESLEY @CRAFT","estimationTemps":0}},"id":10119,"vehiculeLoad":"8%","type":"Bus","numeroEquipement":"21215"},{"localisation":{"lat":35.17934327062474,"lng":-89.93619351333217,"cap":218},"conduite":{"idLigne":90302,"vitesse":15,"destination":"WILLIAM HUDSON ","avanceRetard":"6 min late","arretSuiv":{"nomCommercial":"JACKSON AVE @ORCHI","estimationTemps":0}},"id":10125,"vehiculeLoad":"4%","type":"Bus","numeroEquipement":"460"},{"localisation":{"lat":35.061779869326955,"lng":-90.02370332902267,"cap":275},"conduite":{"idLigne":90285,"vitesse":6,"destination":"BROOKS RD@ 3RD ST","avanceRetard":"7 min late","arretSuiv":{"nomCommercial":"BROOKS @LUCIBILL","estimationTemps":0}},"id":26042,"vehiculeLoad":"6%","type":"Bus","numeroEquipement":"20804"},{"localisation":{"lat":35.22131957730375,"lng":-89.97308927192589,"cap":268},"conduite":{"idLigne":90281,"vitesse":9,"destination":"WILLIAM HUDSON ","avanceRetard":"9 min late","arretSuiv":{"nomCommercial":"FRAYSER @RANGE LINE RD","estimationTemps":0}},"id":26044,"vehiculeLoad":"6%","type":"Bus","numeroEquipement":"20802"},{"localisation":{"lat":35.062217820211956,"lng":-89.99249391283938,"cap":100},"conduite":{"idLigne":90284,"vitesse":0,"destination":"WILLIAM HUDSON ","avanceRetard":"3 min early","arretSuiv":{"nomCommercial":"AIRWAYS BLVD @BROOKS","estimationTemps":0}},"id":25027,"vehiculeLoad":"0%","type":"Bus","numeroEquipement":"22305"},{"localisation":{"lat":35.15972814308887,"lng":-89.97577351044534,"cap":0},"conduite":{"idLigne":90283,"vitesse":9,"destination":"WILLIAM HUDSON ","avanceRetard":"on time","arretSuiv":{"nomCommercial":"NHOLLYWOOD @JACKSON","estimationTemps":0}},"id":25028,"vehiculeLoad":"0%","type":"Bus","numeroEquipement":"22306"},{"localisation":{"lat":35.063244646740486,"lng":-90.06671264849518,"cap":91},"conduite":{"idLigne":90299,"vitesse":8,"destination":"WILLIAM HUDSON ","avanceRetard":"2 min early","arretSuiv":{"nomCommercial":"BROOKS RD @LOTUS","estimationTemps":0}},"id":25029,"vehiculeLoad":"14%","type":"Bus","numeroEquipement":"22301"},{"localisation":{"lat":35.0510598479225,"lng":-89.90118637723295,"cap":274},"conduite":{"idLigne":90297,"vitesse":2,"destination":"WILLIAM HUDSON ","avanceRetard":"on time","arretSuiv":{"nomCommercial":"WINCHESTER @BOXDALE","estimationTemps":0}},"id":25030,"vehiculeLoad":"0%","type":"Bus","numeroEquipement":"22302"},{"localisation":{"lat":35.042497244626965,"lng":-89.94353414939422,"cap":3},"conduite":{"idLigne":90304,"vitesse":15,"destination":"AIRWAYS TRANSIT","avanceRetard":"4 min late","arretSuiv":{"nomCommercial":"CHRISTINE @PRESCOTT","estimationTemps":0}},"id":25032,"vehiculeLoad":"12%","type":"Bus","numeroEquipement":"22304"}]}