{"vehicule":[{"localisation":{"lat":35.16107575668158,"lng":-89.86383389149788,"cap":179},"conduite":{"idLigne":75312,"vitesse":0,"destination":"WOLFCHASE GALLE","avanceRetard":"on time","arretSuiv":{"nomCommercial":"SWTCC","estimationTemps":0}},"id":19045,"vehiculeLoad":"6%","type":"Bus","numeroEquipement":"5004"},{"localisation":{"lat":35.14786875657761,"lng":-90.05171364498484,"cap":20},"conduite":{"idLigne":75295,"vitesse":0,"destination":"WILLIAM HUDSON ","avanceRetard":"on time","arretSuiv":{"nomCommercial":"CIVIC @ MAIN","estimationTemps":0}},"id":15016,"vehiculeLoad":"3%","type":"Trolley","numeroEquipement":"9540"},{"localisation":{"lat":35.134201451327485,"lng":-90.0589933865576,"cap":183},"conduite":{"idLigne":75295,"vitesse":0,"destination":"CENTRAL STATION","avanceRetard":"8 min late","arretSuiv":{"nomCommercial":"CENTRAL STATION","estimationTemps":1}},"id":15017,"vehiculeLoad":"0%","type":"Trolley","numeroEquipement":"9539"},{"localisation":{"lat":35.154052405659684,"lng":-90.0493226798786,"cap":198},"conduite":{"idLigne":75295,"vitesse":5,"destination":"CENTRAL STATION","avanceRetard":"on time","arretSuiv":{"nomCommercial":"CONVENTION@MAIN","estimationTemps":1}},"id":15018,"vehiculeLoad":"5%","type":"Trolley","numeroEquipement":"9455"},{"localisation":{"lat":35.137752940229646,"lng":-90.05665833810355,"cap":211},"conduite":{"idLigne":75295,"vitesse":6,"destination":"CENTRAL STATION","avanceRetard":"on time","arretSuiv":{"nomCommercial":"HULING @ MAIN","estimationTemps":0}},"id":15019,"vehiculeLoad":"0%","type":"Trolley","numeroEquipement":"9453"},{"localisation":{"lat":35.12273515177895,"lng":-89.92719838112058,"cap":272},"conduite":{"idLigne":75301,"vitesse":12,"destination":"WILLIAM HUDSON ","avanceRetard":"3 min early","arretSuiv":{"nomCommercial":"CENTRAL AVE @ROSELAND","estimationTemps":0}},"id":10012,"vehiculeLoad":"12%","type":"Bus","numeroEquipement":"21706"},{"localisation":{"lat":35.15397045787236,"lng":-89.85756924399338,"cap":94},"conduite":{"idLigne":75303,"vitesse":8,"destination":"WILLIAM HUDSON ","avanceRetard":"3 min early","arretSuiv":{"nomCommercial":"STATE RD @MULLINS STATIO","estimationTemps":0}},"id":10013,"vehiculeLoad":"2%","type":"Bus","numeroEquipement":"21705"},{"localisation":{"lat":35.05044595366038,"lng":-89.88625375237659,"cap":91},"conduite":{"idLigne":75297,"vitesse":11,"destination":"CENTENNIAL DR @ HACKS CROSS RD","avanceRetard":"on time","arretSuiv":{"nomCommercial":"WINCHESTER RD @MENDENHALL RD","estimationTemps":0}},"id":10014,"vehiculeLoad":"0%","type":"Bus","numeroEquipement":"21704"},{"localisation":{"lat":35.05169856464663,"lng":-89.92605574077066,"cap":270},"conduite":{"idLigne":75316,"vitesse":3,"destination":"DOUBLE TREE @ PARKROSE RD","avanceRetard":"4 min late","arretSuiv":{"nomCommercial":"WINCHESTER @LAMAR","estimationTemps":0}},"id":10015,"vehiculeLoad":"0%","type":"Bus","numeroEquipement":"21703"},{"localisation":{"lat":35.04381435510252,"lng":-89.79694389550878,"cap":251},"conduite":{"idLigne":75297,"vitesse":0,"destination":"WILLIAM HUDSON ","avanceRetard":"2 min late","arretSuiv":{"nomCommercial":"CENTENNIAL DR @EL RINCON","estimationTemps":0}},"id":10016,"vehiculeLoad":"0%","type":"Bus","numeroEquipement":"21702"},{"localisation":{"lat":35.076693289534894,"lng":-89.93666063326053,"cap":273},"conduite":{"idLigne":75314,"vitesse":13,"destination":"3RD ST @ EASTMAN RD","avanceRetard":"10 min late","arretSuiv":{"nomCommercial":"AMERICAN WAY @LAMAR","estimationTemps":1}},"id":10017,"vehiculeLoad":"0%","type":"Bus","numeroEquipement":"21701"},{"localisation":{"lat":35.043880852088876,"lng":-90.02512224511108,"cap":359},"conduite":{"idLigne":75300,"vitesse":0,"destination":"FRAYSER PLAZA","avanceRetard":"9 min late","arretSuiv":{"nomCommercial":"ELVIS PRESLEY @OLD HICKORY","estimationTemps":1}},"id":10020,"vehiculeLoad":"26%","type":"Bus","numeroEquipement":"21714"},{"localisation":{"lat":35.07833712422651,"lng":-89.98506327486992,"cap":12},"conduite":{"idLigne":75296,"vitesse":8,"destination":"FRAYSER PLAZA","avanceRetard":"6 min late","arretSuiv":{"nomCommercial":"AIRWAYS BLVD @KETCHUM RD","estimationTemps":0}},"id":10021,"vehiculeLoad":"4%","type":"Bus","numeroEquipement":"21712"},{"localisation":{"lat":35.23312350086824,"lng":-89.89320524412175,"cap":144},"conduite":{"idLigne":75302,"vitesse":0,"destination":"WILLIAM HUDSON ","avanceRetard":"on time","arretSuiv":{"nomCommercial":"COVINGTON PIKE @AUSTIN PEAY","estimationTemps":0}},"id":10022,"vehiculeLoad":"26%","type":"Bus","numeroEquipement":"21711"},{"localisation":{"lat":35.062242403852096,"lng":-89.99257899381817,"cap":91},"conduite":{"idLigne":75310,"vitesse":0,"destination":"WILLIAM HUDSON ","avanceRetard":"2 min late","arretSuiv":{"nomCommercial":"DIRECTORS ROW @BROOKS","estimationTemps":1}},"id":10026,"vehiculeLoad":"2%","type":"Bus","numeroEquipement":"21708"},{"localisation":{"lat":35.15851350630229,"lng":-90.04743373725776,"cap":9},"conduite":{"idLigne":75309,"vitesse":0,"destination":"YALE RD @ AUSTIN PEAY HW","avanceRetard":"on time","arretSuiv":{"nomCommercial":"THIRD @MILL","estimationTemps":0}},"id":10028,"vehiculeLoad":"0%","type":"Bus","numeroEquipement":"405"},{"localisation":{"lat":35.02051837966883,"lng":-89.88013922408292,"cap":270},"conduite":{"idLigne":75294,"vitesse":8,"destination":"AMERICAN WAY TR","avanceRetard":"5 min late","arretSuiv":{"nomCommercial":"SHELBY @TUGGLE","estimationTemps":1}},"id":10030,"vehiculeLoad":"0%","type":"Bus","numeroEquipement":"21806"},{"localisation":{"lat":35.20687352282506,"lng":-89.89237612443821,"cap":275},"conduite":{"idLigne":75305,"vitesse":20,"destination":"WILLIAM HUDSON ","avanceRetard":"3 min late","arretSuiv":{"nomCommercial":"STAGE @COVINGTON PIKE","estimationTemps":0}},"id":10031,"vehiculeLoad":"22%","type":"Bus","numeroEquipement":"21805"},{"localisation":{"lat":35.00165495874615,"lng":-89.93638372894175,"cap":277},"conduite":{"idLigne":75314,"vitesse":0,"destination":"RIVERDAL @ WINCH","avanceRetard":"7 min late","arretSuiv":{"nomCommercial":"SHELBY atTCHULAHOMA","estimationTemps":0}},"id":9009,"vehiculeLoad":"2%","type":"Bus","numeroEquipement":"448"},{"localisation":{"lat":35.07302159160047,"lng":-89.94773500951916,"cap":149},"conduite":{"idLigne":75297,"vitesse":11,"destination":"CENTENNIAL DR @ HACKS CROSS RD","avanceRetard":"on time","arretSuiv":{"nomCommercial":"LAMAR @DEMOCRAT","estimationTemps":0}},"id":10033,"vehiculeLoad":"4%","type":"Bus","numeroEquipement":"21803"},{"localisation":{"lat":35.185318033672566,"lng":-89.89645367313213,"cap":180},"conduite":{"idLigne":75312,"vitesse":0,"destination":"WILLIAM HUDSON ","avanceRetard":"2 min late","arretSuiv":{"nomCommercial":"COVINGTON PIKE @COVINGTON WAY","estimationTemps":0}},"id":10035,"vehiculeLoad":"2%","type":"Bus","numeroEquipement":"21801"},{"localisation":{"lat":35.158880773072774,"lng":-90.04644672665614,"cap":110},"conduite":{"idLigne":75292,"vitesse":0,"destination":"WALNUT @ RACINE","avanceRetard":"on time","arretSuiv":{"nomCommercial":"SECOND @JACKSON","estimationTemps":1}},"id":9012,"vehiculeLoad":"2%","type":"Bus","numeroEquipement":"21503"},{"localisation":{"lat":35.21725174251482,"lng":-89.99224514207904,"cap":271},"conduite":{"idLigne":75300,"vitesse":0,"destination":"HOLMES RD @ HUDGINS RD","avanceRetard":"on time","arretSuiv":{"nomCommercial":"FRAYSER PLAZA","estimationTemps":0}},"id":10037,"vehiculeLoad":"0%","type":"Bus","numeroEquipement":"412"},{"localisation":{"lat":35.10350856192878,"lng":-89.93071205959852,"cap":2},"conduite":{"idLigne":75291,"vitesse":14,"destination":"WILLIAM HUDSON ","avanceRetard":"on time","arretSuiv":{"nomCommercial":"GETWELL @STUART","estimationTemps":0}},"id":10038,"vehiculeLoad":"6%","type":"Bus","numeroEquipement":"414"},{"localisation":{"lat":35.11946213551086,"lng":-89.98459217324819,"cap":94},"conduite":{"idLigne":75317,"vitesse":0,"destination":"KNIGHT ARNOLD @ RIDGEWAY RD","avanceRetard":"2 min late","arretSuiv":{"nomCommercial":"SOUTHERN @E PARKWAY","estimationTemps":1}},"id":10040,"vehiculeLoad":"2%","type":"Bus","numeroEquipement":"417"},{"localisation":{"lat":35.07639948446589,"lng":-89.93073983435006,"cap":271},"conduite":{"idLigne":75297,"vitesse":0,"destination":"WILLIAM HUDSON ","avanceRetard":"4 min early","arretSuiv":{"nomCommercial":"AMERICAN WAY TR","estimationTemps":0}},"id":10044,"vehiculeLoad":"6%","type":"Bus","numeroEquipement":"21807"},{"localisation":{"lat":35.121583621860985,"lng":-90.00876148275623,"cap":308},"conduite":{"idLigne":75297,"vitesse":14,"destination":"WILLIAM HUDSON ","avanceRetard":"on time","arretSuiv":{"nomCommercial":"LAMAR AVE @WILLETT","estimationTemps":0}},"id":10046,"vehiculeLoad":"4%","type":"Bus","numeroEquipement":"428"},{"localisation":{"lat":35.16577657488263,"lng":-89.94647337687795,"cap":206},"conduite":{"idLigne":75291,"vitesse":24,"destination":"AMERICAN WAY TR","avanceRetard":"on time","arretSuiv":{"nomCommercial":"NATIONAL @FARMVILLE","estimationTemps":0}},"id":10050,"vehiculeLoad":"8%","type":"Bus","numeroEquipement":"4011"},{"localisation":{"lat":35.18442850403039,"lng":-89.9752407906859,"cap":166},"conduite":{"idLigne":75296,"vitesse":18,"destination":"AIRWAYS TRANSIT","avanceRetard":"2 min early","arretSuiv":{"nomCommercial":"HOLLYWOOD @MIDWAY","estimationTemps":0}},"id":10053,"vehiculeLoad":"4%","type":"Bus","numeroEquipement":"21502"},{"localisation":{"lat":35.043076482047,"lng":-89.9536371855771,"cap":91},"conduite":{"idLigne":75304,"vitesse":16,"destination":"AMERICAN WAY TR","avanceRetard":"2 min late","arretSuiv":{"nomCommercial":"CHRISTINE atPRESCOTT","estimationTemps":0}},"id":10061,"vehiculeLoad":"0%","type":"Bus","numeroEquipement":"439"},{"localisation":{"lat":35.065993588897214,"lng":-90.05881369919783,"cap":5},"conduite":{"idLigne":75299,"vitesse":13,"destination":"WILLIAM HUDSON ","avanceRetard":"on time","arretSuiv":{"nomCommercial":"3RD ST @PEEBLES RD","estimationTemps":0}},"id":10062,"vehiculeLoad":"6%","type":"Bus","numeroEquipement":"4007"},{"localisation":{"lat":35.1582328437313,"lng":-90.04754238968403,"cap":13},"conduite":{"idLigne":75302,"vitesse":0,"destination":"METHODIST HOSPI","avanceRetard":"on time","arretSuiv":{"nomCommercial":"AW WILLIS @THIRD","estimationTemps":1}},"id":8014,"vehiculeLoad":"24%","type":"Bus","numeroEquipement":"21713"},{"localisation":{"lat":35.09843835850609,"lng":-89.84118184065291,"cap":106},"conduite":{"idLigne":75301,"vitesse":0,"destination":"EXETER RD @ POPLAR AVE","avanceRetard":"on time","arretSuiv":{"nomCommercial":"POPLAR AVE @KIRBY PKWY","estimationTemps":0}},"id":10065,"vehiculeLoad":"20%","type":"Bus","numeroEquipement":"4020"},{"localisation":{"lat":35.07580166387008,"lng":-89.9323570256287,"cap":189},"conduite":{"idLigne":75294,"vitesse":0,"destination":"AMERICAN WAY TR","avanceRetard":"on time","arretSuiv":null},"id":10068,"vehiculeLoad":"0%","type":"Bus","numeroEquipement":"4023"},{"localisation":{"lat":35.15627993692935,"lng":-90.04798277698673,"cap":219},"conduite":{"idLigne":75311,"vitesse":0,"destination":"ALICE AVE @ BENTON ST","avanceRetard":"on time","arretSuiv":{"nomCommercial":"SECOND @JACKSON","estimationTemps":1}},"id":10069,"vehiculeLoad":"0%","type":"Bus","numeroEquipement":"4024"},{"localisation":{"lat":35.17445049735892,"lng":-89.96899648647741,"cap":273},"conduite":{"idLigne":75291,"vitesse":14,"destination":"WILLIAM HUDSON ","avanceRetard":"on time","arretSuiv":{"nomCommercial":"CHELSEA AVE @FAIRFAX ST","estimationTemps":0}},"id":10071,"vehiculeLoad":"2%","type":"Bus","numeroEquipement":"440"},{"localisation":{"lat":35.05085508615869,"lng":-90.061496232541,"cap":197},"conduite":{"idLigne":75299,"vitesse":18,"destination":"HOLMES RD @ THIRD ST","avanceRetard":"3 min late","arretSuiv":{"nomCommercial":"FAIRWAY @THIRD","estimationTemps":0}},"id":10074,"vehiculeLoad":"12%","type":"Bus","numeroEquipement":"443"},{"localisation":{"lat":35.13583890863251,"lng":-89.96229700208521,"cap":199},"conduite":{"idLigne":75292,"vitesse":1,"destination":"WALNUT @ RACINE","avanceRetard":"19 min late","arretSuiv":{"nomCommercial":"WALNUT GROVE atEASTVIEW","estimationTemps":0}},"id":10076,"vehiculeLoad":"14%","type":"Bus","numeroEquipement":"445"},{"localisation":{"lat":35.19594266345102,"lng":-89.90190204711948,"cap":126},"conduite":{"idLigne":75298,"vitesse":0,"destination":"AMERICAN WAY TR","avanceRetard":"3 min late","arretSuiv":{"nomCommercial":"RALEIGH LAGRANG @BATTLE CREEK","estimationTemps":0}},"id":10077,"vehiculeLoad":"0%","type":"Bus","numeroEquipement":"446"},{"localisation":{"lat":35.132825559391314,"lng":-90.05942330323447,"cap":92},"conduite":{"idLigne":75307,"vitesse":0,"destination":"WILLIAM HUDSON ","avanceRetard":"6 min early","arretSuiv":{"nomCommercial":"BULTER-MAIN/TRO","estimationTemps":0}},"id":10089,"vehiculeLoad":"7%","type":"Bus","numeroEquipement":"607"},{"localisation":{"lat":35.035062754356964,"lng":-89.85631211957715,"cap":268},"conduite":{"idLigne":75314,"vitesse":7,"destination":"3RD ST @ EASTMAN RD","avanceRetard":"5 min late","arretSuiv":{"nomCommercial":"RAINES @BERRY BROOK","estimationTemps":1}},"id":10101,"vehiculeLoad":"6%","type":"Bus","numeroEquipement":"21207"},{"localisation":{"lat":35.09502685503456,"lng":-89.85981591493524,"cap":98},"conduite":{"idLigne":75315,"vitesse":0,"destination":"PRIMACY PKWY @ RIDGEWAY RD","avanceRetard":"9 min late","arretSuiv":{"nomCommercial":"PRIMACY PKWY @ RIDGEWAY RD","estimationTemps":0}},"id":10104,"vehiculeLoad":"14%","type":"Bus","numeroEquipement":"450"},{"localisation":{"lat":35.15893152600033,"lng":-90.04663889955788,"cap":106},"conduite":{"idLigne":75315,"vitesse":0,"destination":"PRIMACY PKWY @ RIDGEWAY RD","avanceRetard":"on time","arretSuiv":{"nomCommercial":"SECOND @JACKSON","estimationTemps":1}},"id":10106,"vehiculeLoad":"4%","type":"Bus","numeroEquipement":"452"},{"localisation":{"lat":35.12223349671094,"lng":-89.9336965839842,"cap":180},"conduite":{"idLigne":75317,"vitesse":9,"destination":"WILLIAM HUDSON ","avanceRetard":"on time","arretSuiv":{"nomCommercial":"ZACH H CURLIN @DESOTO","estimationTemps":0}},"id":10107,"vehiculeLoad":"2%","type":"Bus","numeroEquipement":"453"},{"localisation":{"lat":35.12392327221161,"lng":-89.84929483144249,"cap":138},"conduite":{"idLigne":75306,"vitesse":13,"destination":"WILLIAM HUDSON ","avanceRetard":"on time","arretSuiv":{"nomCommercial":"HUMPHREYS @E SHADY GROVE","estimationTemps":0}},"id":10109,"vehiculeLoad":"0%","type":"Bus","numeroEquipement":"454"},{"localisation":{"lat":35.20725710789296,"lng":-89.99024516667035,"cap":359},"conduite":{"idLigne":75296,"vitesse":3,"destination":"FRAYSER PLAZA","avanceRetard":"3 min early","arretSuiv":{"nomCommercial":"UNIVERSITY @WILLOW WOOD","estimationTemps":0}},"id":10110,"vehiculeLoad":"6%","type":"Bus","numeroEquipement":"455"},{"localisation":{"lat":35.15108299479008,"lng":-90.04767900487924,"cap":18},"conduite":{"idLigne":75293,"vitesse":18,"destination":"WILLIAM HUDSON ","avanceRetard":"on time","arretSuiv":{"nomCommercial":"THIRD @MARKET","estimationTemps":0}},"id":10111,"vehiculeLoad":"6%","type":"Bus","numeroEquipement":"456"},{"localisation":{"lat":35.06006199494867,"lng":-89.85582382299978,"cap":109},"conduite":{"idLigne":75317,"vitesse":0,"destination":"WILLIAM HUDSON ","avanceRetard":"3 min late","arretSuiv":{"nomCommercial":"KNIGHT ARNOLD @KNIGHT TRAILS ","estimationTemps":1}},"id":10115,"vehiculeLoad":"10%","type":"Bus","numeroEquipement":"4026"},{"localisation":{"lat":35.15796279350634,"lng":-90.0476718322779,"cap":3},"conduite":{"idLigne":75299,"vitesse":0,"destination":"JONETTA ST @ HOLMES RD","avanceRetard":"on time","arretSuiv":{"nomCommercial":"SECOND @MARKET","estimationTemps":1}},"id":10119,"vehiculeLoad":"2%","type":"Bus","numeroEquipement":"21215"},{"localisation":{"lat":35.04959731608783,"lng":-90.11198650891222,"cap":268},"conduite":{"idLigne":75316,"vitesse":14,"destination":"DOUBLE TREE @ PARKROSE RD","avanceRetard":"on time","arretSuiv":{"nomCommercial":"FIELDS @SEWANEE","estimationTemps":1}},"id":10120,"vehiculeLoad":"0%","type":"Bus","numeroEquipement":"21214"},{"localisation":{"lat":35.155999566677544,"lng":-90.04773957400792,"cap":288},"conduite":{"idLigne":75317,"vitesse":0,"destination":"CENTRAL AVE @ U-M CROSSWALK","avanceRetard":"on time","arretSuiv":{"nomCommercial":"SECOND @MARKET","estimationTemps":1}},"id":10127,"vehiculeLoad":"4%","type":"Bus","numeroEquipement":"462"}]}