{"vehicule":[{"localisation":{"lat":35.15795045468792,"lng":-90.01176449837209,"cap":9},"conduite":{"idLigne":89229,"vitesse":0,"destination":"FRAYSER at WOODROW","avanceRetard":"on time","arretSuiv":{"nomCommercial":"WATKINS @JACKSON","estimationTemps":0}},"id":22023,"vehiculeLoad":"2%","type":"Bus","numeroEquipement":"22201"},{"localisation":{"lat":35.15929928225527,"lng":-90.04435444674995,"cap":18},"conduite":{"idLigne":89235,"vitesse":9,"destination":"FLETCHER TRACE @ STAGE RD","avanceRetard":"8 min late","arretSuiv":{"nomCommercial":"THIRD @LOONEY","estimationTemps":0}},"id":22026,"vehiculeLoad":"12%","type":"Bus","numeroEquipement":"4031"},{"localisation":{"lat":35.10642438118154,"lng":-89.880200483589,"cap":107},"conduite":{"idLigne":89228,"vitesse":18,"destination":"EXETER RD @ POPLAR AVE","avanceRetard":"2 min late","arretSuiv":{"nomCommercial":"POPLAR @JUNE","estimationTemps":0}},"id":21021,"vehiculeLoad":"2%","type":"Bus","numeroEquipement":"4016"},{"localisation":{"lat":35.02098741502007,"lng":-90.0290258783889,"cap":269},"conduite":{"idLigne":89242,"vitesse":14,"destination":"DOUBLE TREE @ PARKROSE RD","avanceRetard":"on time","arretSuiv":{"nomCommercial":"SHELBY DR @LINWOOD","estimationTemps":0}},"id":19042,"vehiculeLoad":"10%","type":"Bus","numeroEquipement":"21209"},{"localisation":{"lat":35.15139241853211,"lng":-90.04996375146253,"cap":194},"conduite":{"idLigne":89234,"vitesse":2,"destination":"CENTRAL STATION","avanceRetard":"on time","arretSuiv":{"nomCommercial":"MAIN ST @CIVIC CTR/OB","estimationTemps":1}},"id":15015,"vehiculeLoad":"10%","type":"Trolley","numeroEquipement":"9234"},{"localisation":{"lat":35.134327618322665,"lng":-90.058990152632,"cap":188},"conduite":{"idLigne":89234,"vitesse":0,"destination":"CENTRAL STATION","avanceRetard":"8 min late","arretSuiv":{"nomCommercial":"CENTRAL STATION","estimationTemps":1}},"id":15017,"vehiculeLoad":"3%","type":"Trolley","numeroEquipement":"9539"},{"localisation":{"lat":35.13325312502854,"lng":-90.0589903957777,"cap":4},"conduite":{"idLigne":89234,"vitesse":0,"destination":"CENTRAL STATION","avanceRetard":"20 min late","arretSuiv":{"nomCommercial":"CENTRAL STATION","estimationTemps":0}},"id":15018,"vehiculeLoad":"1%","type":"Trolley","numeroEquipement":"9455"},{"localisation":{"lat":35.14167225547264,"lng":-90.05429259833465,"cap":178},"conduite":{"idLigne":89234,"vitesse":0,"destination":"CENTRAL STATION","avanceRetard":"3 min late","arretSuiv":{"nomCommercial":"MAIN ST @BEALE ST/OB","estimationTemps":0}},"id":15019,"vehiculeLoad":"8%","type":"Trolley","numeroEquipement":"9453"},{"localisation":{"lat":35.05047819358529,"lng":-89.88643677262807,"cap":92},"conduite":{"idLigne":89232,"vitesse":2,"destination":"CENTENNIAL DR @ HACKS CROSS RD","avanceRetard":"3 min early","arretSuiv":{"nomCommercial":"SECOND @EXCHANGE","estimationTemps":-71}},"id":10011,"vehiculeLoad":"18%","type":"Bus","numeroEquipement":"21707"},{"localisation":{"lat":35.09966969199944,"lng":-90.01339705442555,"cap":9},"conduite":{"idLigne":89239,"vitesse":8,"destination":"WILLIAM HUDSON ","avanceRetard":"on time","arretSuiv":{"nomCommercial":"PERSON @PILLOW","estimationTemps":0}},"id":10014,"vehiculeLoad":"6%","type":"Bus","numeroEquipement":"21704"},{"localisation":{"lat":35.12285808515034,"lng":-90.01090315904813,"cap":123},"conduite":{"idLigne":89232,"vitesse":1,"destination":"CENTENNIAL DR @ HACKS CROSS RD","avanceRetard":"2 min late","arretSuiv":{"nomCommercial":"LAMAR @WILLETT","estimationTemps":0}},"id":10015,"vehiculeLoad":"14%","type":"Bus","numeroEquipement":"21703"},{"localisation":{"lat":35.1351399011048,"lng":-89.99038534522028,"cap":186},"conduite":{"idLigne":89240,"vitesse":14,"destination":"CENTRAL AVE @ U-M CROSSWALK","avanceRetard":"on time","arretSuiv":{"nomCommercial":"SECOND @EXCHANGE","estimationTemps":-27}},"id":10017,"vehiculeLoad":"8%","type":"Bus","numeroEquipement":"21701"},{"localisation":{"lat":35.149174679238854,"lng":-89.92705890748367,"cap":271},"conduite":{"idLigne":89226,"vitesse":10,"destination":"WILLIAM HUDSON ","avanceRetard":"on time","arretSuiv":{"nomCommercial":"SUMMER AVE @N GRAHAM ST","estimationTemps":0}},"id":10018,"vehiculeLoad":"10%","type":"Bus","numeroEquipement":"21710"},{"localisation":{"lat":35.17660262388187,"lng":-89.97539404735554,"cap":185},"conduite":{"idLigne":89233,"vitesse":10,"destination":"AIRWAYS TRANSIT","avanceRetard":"2 min early","arretSuiv":{"nomCommercial":"HOLLYWOOD @CHELSEA","estimationTemps":0}},"id":10020,"vehiculeLoad":"12%","type":"Bus","numeroEquipement":"21714"},{"localisation":{"lat":35.11084892718356,"lng":-90.03041723084306,"cap":182},"conduite":{"idLigne":89239,"vitesse":8,"destination":"AIRWAYS TRANSIT","avanceRetard":"2 min late","arretSuiv":{"nomCommercial":"PERSON @CINCINATTI","estimationTemps":6}},"id":10021,"vehiculeLoad":"0%","type":"Bus","numeroEquipement":"21712"},{"localisation":{"lat":35.14064195353786,"lng":-90.01804541110661,"cap":187},"conduite":{"idLigne":89249,"vitesse":9,"destination":"CLAYBROOK @ MADISON","avanceRetard":"on time","arretSuiv":{"nomCommercial":"CLAYBROOK @ MADISON","estimationTemps":0}},"id":10023,"vehiculeLoad":"4%","type":"Bus","numeroEquipement":"3007"},{"localisation":{"lat":35.09264161124801,"lng":-89.80247622603217,"cap":186},"conduite":{"idLigne":89228,"vitesse":0,"destination":"WILLIAM HUDSON ","avanceRetard":"2 min late","arretSuiv":{"nomCommercial":"EXETER @POPLAR","estimationTemps":0}},"id":10033,"vehiculeLoad":"4%","type":"Bus","numeroEquipement":"21803"},{"localisation":{"lat":35.034473131369126,"lng":-89.96366397732987,"cap":358},"conduite":{"idLigne":89244,"vitesse":0,"destination":"BROOKS RD@ 3RD ST","avanceRetard":"4 min late","arretSuiv":{"nomCommercial":"SWINNEAatRUNWAY","estimationTemps":0}},"id":10034,"vehiculeLoad":"0%","type":"Bus","numeroEquipement":"21802"},{"localisation":{"lat":35.10590475895231,"lng":-89.91564680839554,"cap":359},"conduite":{"idLigne":89240,"vitesse":0,"destination":"WILLIAM HUDSON ","avanceRetard":"2 min early","arretSuiv":{"nomCommercial":"PARK @CHERRY","estimationTemps":0}},"id":10035,"vehiculeLoad":"8%","type":"Bus","numeroEquipement":"21801"},{"localisation":{"lat":35.10895886642625,"lng":-90.00379589212102,"cap":92},"conduite":{"idLigne":89243,"vitesse":13,"destination":"PRIMACY PKWY @ RIDGEWAY RD","avanceRetard":"on time","arretSuiv":{"nomCommercial":"SOUTH PARKWAY @OAKLAWN","estimationTemps":0}},"id":10042,"vehiculeLoad":"20%","type":"Bus","numeroEquipement":"21809"},{"localisation":{"lat":35.14941762495294,"lng":-89.94487530931906,"cap":90},"conduite":{"idLigne":89226,"vitesse":0,"destination":"SWTCC","avanceRetard":"on time","arretSuiv":{"nomCommercial":"SUMMER AVE @HIGHLAND","estimationTemps":0}},"id":10043,"vehiculeLoad":"18%","type":"Bus","numeroEquipement":"21808"},{"localisation":{"lat":35.16689371096572,"lng":-89.950315729435,"cap":225},"conduite":{"idLigne":89227,"vitesse":19,"destination":"WILLIAM HUDSON ","avanceRetard":"on time","arretSuiv":{"nomCommercial":"JACKSON AVE @ROSEAMOND","estimationTemps":0}},"id":10044,"vehiculeLoad":"32%","type":"Bus","numeroEquipement":"21807"},{"localisation":{"lat":35.05244120791932,"lng":-90.02511027808613,"cap":2},"conduite":{"idLigne":89229,"vitesse":3,"destination":"FRAYSER at WOODROW","avanceRetard":"2 min late","arretSuiv":{"nomCommercial":"ELVIS PRESLEY @WINCHESTER","estimationTemps":0}},"id":10048,"vehiculeLoad":"16%","type":"Bus","numeroEquipement":"21501"},{"localisation":{"lat":35.21286979497523,"lng":-90.01630826281546,"cap":62},"conduite":{"idLigne":89248,"vitesse":0,"destination":"YALE RD @ AUSTIN PEAY HW","avanceRetard":"on time","arretSuiv":{"nomCommercial":"DELLWOOD @CANFIELD","estimationTemps":0}},"id":10053,"vehiculeLoad":"20%","type":"Bus","numeroEquipement":"21502"},{"localisation":{"lat":35.001617754307446,"lng":-89.93508172842252,"cap":90},"conduite":{"idLigne":89238,"vitesse":0,"destination":"AMERICAN WAY TR","avanceRetard":"on time","arretSuiv":{"nomCommercial":"GETWELL @HOLMES","estimationTemps":0}},"id":10056,"vehiculeLoad":"4%","type":"Bus","numeroEquipement":"437"},{"localisation":{"lat":35.107590409499636,"lng":-90.0517516902037,"cap":154},"conduite":{"idLigne":89235,"vitesse":2,"destination":"ALICE AVE @ BENTON ST","avanceRetard":"5 min late","arretSuiv":{"nomCommercial":"LATHAM @SPARKWAY","estimationTemps":0}},"id":10057,"vehiculeLoad":"2%","type":"Bus","numeroEquipement":"4004"},{"localisation":{"lat":35.14168497163229,"lng":-89.98977427493664,"cap":96},"conduite":{"idLigne":89228,"vitesse":19,"destination":"EXETER RD @ POPLAR AVE","avanceRetard":"on time","arretSuiv":{"nomCommercial":"POPLAR @COX","estimationTemps":0}},"id":10065,"vehiculeLoad":"26%","type":"Bus","numeroEquipement":"4020"},{"localisation":{"lat":35.174177979570665,"lng":-89.96320995384872,"cap":92},"conduite":{"idLigne":89237,"vitesse":10,"destination":"AMERICAN WAY TR","avanceRetard":"on time","arretSuiv":{"nomCommercial":"CHELSEA AVE @WARFORD","estimationTemps":0}},"id":10072,"vehiculeLoad":"10%","type":"Bus","numeroEquipement":"441"},{"localisation":{"lat":35.063261365827294,"lng":-90.07322366156652,"cap":91},"conduite":{"idLigne":89230,"vitesse":4,"destination":"WILLIAM HUDSON ","avanceRetard":"on time","arretSuiv":{"nomCommercial":"BROOKS RD @REDBUD","estimationTemps":1}},"id":10074,"vehiculeLoad":"4%","type":"Bus","numeroEquipement":"443"},{"localisation":{"lat":35.15802180794772,"lng":-89.97565966092209,"cap":273},"conduite":{"idLigne":89246,"vitesse":0,"destination":"WILLIAM HUDSON ","avanceRetard":"3 min late","arretSuiv":{"nomCommercial":"HOLLYWOOD @JACKSON","estimationTemps":0}},"id":10076,"vehiculeLoad":"2%","type":"Bus","numeroEquipement":"445"},{"localisation":{"lat":35.02094019741574,"lng":-89.98983819847234,"cap":0},"conduite":{"idLigne":89229,"vitesse":0,"destination":"AIRWAYS TRANSIT","avanceRetard":"12 min late","arretSuiv":{"nomCommercial":"SHELBY DR @AIRWAYS BLVD","estimationTemps":0}},"id":10077,"vehiculeLoad":"4%","type":"Bus","numeroEquipement":"446"},{"localisation":{"lat":35.13707104694712,"lng":-90.01669089534298,"cap":191},"conduite":{"idLigne":89229,"vitesse":0,"destination":"AIRWAYS TRANSIT","avanceRetard":"3 min early","arretSuiv":{"nomCommercial":"BELLEVUE @CARR AVE","estimationTemps":3}},"id":10079,"vehiculeLoad":"10%","type":"Bus","numeroEquipement":"447"},{"localisation":{"lat":35.10481585548266,"lng":-89.9306837453633,"cap":0},"conduite":{"idLigne":89237,"vitesse":0,"destination":"WILLIAM HUDSON ","avanceRetard":"on time","arretSuiv":{"nomCommercial":"GETWELL RD @PARK AVE","estimationTemps":0}},"id":10083,"vehiculeLoad":"0%","type":"Bus","numeroEquipement":"449"},{"localisation":{"lat":35.21768341074559,"lng":-90.00568478489124,"cap":274},"conduite":{"idLigne":89248,"vitesse":11,"destination":"WILLIAM HUDSON ","avanceRetard":"on time","arretSuiv":{"nomCommercial":"FRAYSER @FRAYSER SCHOOL","estimationTemps":0}},"id":10104,"vehiculeLoad":"6%","type":"Bus","numeroEquipement":"450"},{"localisation":{"lat":35.07193572442082,"lng":-89.91444146398885,"cap":272},"conduite":{"idLigne":89232,"vitesse":18,"destination":"WILLIAM HUDSON ","avanceRetard":"2 min early","arretSuiv":{"nomCommercial":"AMERICAN WAY @CHERRY RD","estimationTemps":0}},"id":10106,"vehiculeLoad":"24%","type":"Bus","numeroEquipement":"452"},{"localisation":{"lat":35.12943000264524,"lng":-90.06392773866817,"cap":90},"conduite":{"idLigne":89250,"vitesse":8,"destination":"WILLIAM HUDSON ","avanceRetard":"on time","arretSuiv":{"nomCommercial":"CENTRAL STATION","estimationTemps":2}},"id":10108,"vehiculeLoad":"0%","type":"Bus","numeroEquipement":"2006"},{"localisation":{"lat":35.0995860570537,"lng":-90.06522406298907,"cap":185},"conduite":{"idLigne":89247,"vitesse":3,"destination":"AIRWAYS TRANSIT","avanceRetard":"2 min late","arretSuiv":{"nomCommercial":"KANSAS @VAAL AVE","estimationTemps":0}},"id":10109,"vehiculeLoad":"2%","type":"Bus","numeroEquipement":"454"},{"localisation":{"lat":35.1023879976531,"lng":-90.07321513522913,"cap":7},"conduite":{"idLigne":89247,"vitesse":6,"destination":"WILLIAM HUDSON ","avanceRetard":"on time","arretSuiv":{"nomCommercial":"SWIFT @FIELDS","estimationTemps":0}},"id":10110,"vehiculeLoad":"12%","type":"Bus","numeroEquipement":"455"},{"localisation":{"lat":35.105320653900094,"lng":-89.91580148287257,"cap":181},"conduite":{"idLigne":89240,"vitesse":11,"destination":"KNIGHT ARNOLD @ RIDGEWAY RD","avanceRetard":"2 min late","arretSuiv":{"nomCommercial":"CHERRY @HAVERHILL","estimationTemps":0}},"id":10113,"vehiculeLoad":"10%","type":"Bus","numeroEquipement":"458"},{"localisation":{"lat":35.132708766641386,"lng":-89.96140014300097,"cap":295},"conduite":{"idLigne":89241,"vitesse":6,"destination":"WALNUT @ RACINE","avanceRetard":"2 min late","arretSuiv":{"nomCommercial":"POPLAR @TILLMAN","estimationTemps":0}},"id":10115,"vehiculeLoad":"16%","type":"Bus","numeroEquipement":"4026"},{"localisation":{"lat":35.09401504809383,"lng":-90.05609528731522,"cap":184},"conduite":{"idLigne":89230,"vitesse":0,"destination":"JONETTA ST @ HOLMES RD","avanceRetard":"2 min late","arretSuiv":{"nomCommercial":"THIRD @FERNWOOD","estimationTemps":0}},"id":10125,"vehiculeLoad":"14%","type":"Bus","numeroEquipement":"460"},{"localisation":{"lat":35.060699881555756,"lng":-89.992248652445,"cap":265},"conduite":{"idLigne":89245,"vitesse":6,"destination":"WILLIAM HUDSON ","avanceRetard":"on time","arretSuiv":{"nomCommercial":"DIRECTORS ROW @BROOKS","estimationTemps":0}},"id":26038,"vehiculeLoad":"2%","type":"Bus","numeroEquipement":"20807"},{"localisation":{"lat":35.127095370482394,"lng":-89.9453536542778,"cap":182},"conduite":{"idLigne":89224,"vitesse":11,"destination":"WILLIAM HUDSON ","avanceRetard":"7 min late","arretSuiv":{"nomCommercial":"HIGHLAND ST @WINDOVER","estimationTemps":0}},"id":26042,"vehiculeLoad":"0%","type":"Bus","numeroEquipement":"20804"},{"localisation":{"lat":35.0204697334901,"lng":-89.86612379873321,"cap":359},"conduite":{"idLigne":89244,"vitesse":10,"destination":"RIVERDAL @ WINCH","avanceRetard":"5 min late","arretSuiv":{"nomCommercial":"HICKORY HILL atHICKORY CMMS","estimationTemps":0}},"id":26043,"vehiculeLoad":"2%","type":"Bus","numeroEquipement":"20803"},{"localisation":{"lat":35.05345566747976,"lng":-89.98822668060039,"cap":254},"conduite":{"idLigne":89225,"vitesse":15,"destination":"AIRWAYS TRANSIT","avanceRetard":"3 min early","arretSuiv":{"nomCommercial":"AIRWAYS BLVD @WINCHESTER","estimationTemps":0}},"id":26045,"vehiculeLoad":"0%","type":"Bus","numeroEquipement":"20801"},{"localisation":{"lat":35.19389062793999,"lng":-89.8964940245195,"cap":300},"conduite":{"idLigne":89231,"vitesse":0,"destination":"YALE RD @ AUSTIN PEAY HW","avanceRetard":"on time","arretSuiv":{"nomCommercial":"RALEIGH LAGRANG @COVINGTON PI","estimationTemps":0}},"id":25027,"vehiculeLoad":"10%","type":"Bus","numeroEquipement":"22305"},{"localisation":{"lat":35.157903546363976,"lng":-89.97352904127408,"cap":90},"conduite":{"idLigne":89227,"vitesse":11,"destination":"METHODIST HOSPI","avanceRetard":"on time","arretSuiv":{"nomCommercial":"JACKSON @COLUMBIA","estimationTemps":0}},"id":25029,"vehiculeLoad":"40%","type":"Bus","numeroEquipement":"22301"},{"localisation":{"lat":35.10777938792153,"lng":-89.95768730975678,"cap":272},"conduite":{"idLigne":89243,"vitesse":14,"destination":"WILLIAM HUDSON ","avanceRetard":"3 min late","arretSuiv":{"nomCommercial":"PARK @AUBRA","estimationTemps":0}},"id":25031,"vehiculeLoad":"14%","type":"Bus","numeroEquipement":"22303"},{"localisation":{"lat":35.049921293636885,"lng":-89.81014392717488,"cap":100},"conduite":{"idLigne":89232,"vitesse":0,"destination":"CENTENNIAL DR @ HACKS CROSS RD","avanceRetard":"2 min late","arretSuiv":{"nomCommercial":"WINCHESTER @CENTENNIAL DR","estimationTemps":0}},"id":25032,"vehiculeLoad":"30%","type":"Bus","numeroEquipement":"22304"},{"localisation":{"lat":35.21161052216545,"lng":-90.00372241172116,"cap":182},"conduite":{"idLigne":89233,"vitesse":13,"destination":"FRAYSER PLAZA","avanceRetard":"2 min late","arretSuiv":{"nomCommercial":"WATKINS @DRIFTWOOD","estimationTemps":0}},"id":24024,"vehiculeLoad":"10%","type":"Bus","numeroEquipement":"4030"}]}